Workbook

Sheet Resumo
A1: Resumo Anual — Controle de Gastos 2025
A2: Mês | B2: Receita | C2: Total Gastos | D2: Saldo Final | E2: Meta Saldo | F2: Meta Batida?
A3: Janeiro | B3: =Janeiro!B5 -> 2660 | C3: =Janeiro!B14+Janeiro!B24 -> 2283.41 | D3: =Janeiro!B26 -> 376.59 | E3: 200 | F3: =IF(D3>=E3,"✅ Sim","❌ Não") -> ✅ Sim
A4: Fevereiro | B4: =Fevereiro!B5 -> 2962 | C4: =Fevereiro!B14+Fevereiro!B24 -> 2766.1 | D4: =Fevereiro!B26 -> 195.9 | E4: 200 | F4: =IF(D4>=E4,"✅ Sim","❌ Não") -> ❌ Não
A5: Março | B5: =Março!B5 -> 2340 | C5: =Março!B14+Março!B24 -> 2323.2 | D5: =Março!B26 -> 16.8 | E5: 200 | F5: =IF(D5>=E5,"✅ Sim","❌ Não") -> ❌ Não
A6: Abril | B6: =Abril!B5 -> 2460 | C6: =Abril!B14+Abril!B24 -> 2260.51 | D6: =Abril!B26 -> 199.49 | E6: 200 | F6: =IF(D6>=E6,"✅ Sim","❌ Não") -> ❌ Não
A7: TOTAL | B7: =SUM(B3:B6) -> 10422 | C7: =SUM(C3:C6) -> 9633.22 | D7: =SUM(D3:D6) -> 788.78

Sheet Janeiro
A1: Controle de Gastos — Janeiro 2025
A2: RECEITAS | B2: Valor (R$)
A3: Salário | B3: 2160
A4: Comissão | B4: 500
A5: Total Receitas | B5: =SUM(B3:B4) -> 2660
A7: GASTOS FIXOS | B7: Valor (R$)
A8: Aluguel | B8: 880
A9: Luz | B9: 90
A10: Internet | B10: 59.9
A11: 4G | B11: 81.9
A12: Faculdade | B12: 157.9
A13: Alimentação | B13: 500
A14: Total Fixos | B14: =SUM(B8:B13) -> 1769.7
A16: Saldo após Fixos | B16: =B5-B14 -> 890.3
A18: GASTOS VARIÁVEIS | B18: Valor (R$)
A19: Crédito | B19: 200.71
A20: Lazer | B20: 100
A21: Investimentos | B21: 183
A22: Corte | B22: 30
A23: Imprevistos | B23: 0
A24: Total Variáveis | B24: =SUM(B19:B23) -> 513.71
A26: SALDO FINAL | B26: =B5-B14-B24 -> 376.59

Sheet Fevereiro
A1: Controle de Gastos — Fevereiro 2025
A2: RECEITAS | B2: Valor (R$)
A3: Salário | B3: 2462
A4: Comissão | B4: 500
A5: Total Receitas | B5: =SUM(B3:B4) -> 2962
A7: GASTOS FIXOS | B7: Valor (R$)
A8: Aluguel | B8: 880
A9: Luz | B9: 90
A10: Internet | B10: 59.9
A11: 4G | B11: 81.9
A12: Faculdade | B12: 157.9
A13: Alimentação | B13: 500
A14: Total Fixos | B14: =SUM(B8:B13) -> 1769.7
A16: Saldo após Fixos | B16: =B5-B14 -> 1192.3
A18: GASTOS VARIÁVEIS | B18: Valor (R$)
A19: Crédito | B19: 369.75
A20: Lazer | B20: 300
A21: Investimentos | B21: 206.65
A22: Corte | B22: 0
A23: Imprevistos | B23: 120
A24: Total Variáveis | B24: =SUM(B19:B23) -> 996.4
A26: SALDO FINAL | B26: =B5-B14-B24 -> 195.9

Sheet Março
A1: Controle de Gastos — Março 2025
A2: RECEITAS | B2: Valor (R$)
A3: Salário | B3: 1840
A4: Comissão | B4: 500
A5: Total Receitas | B5: =SUM(B3:B4) -> 2340
A7: GASTOS FIXOS | B7: Valor (R$)
A8: Aluguel | B8: 880
A9: Luz | B9: 90
A10: Internet | B10: 59.9
A11: 4G | B11: 81.9
A12: Faculdade | B12: 157.9
A13: Alimentação | B13: 500
A14: Total Fixos | B14: =SUM(B8:B13) -> 1769.7
A16: Saldo após Fixos | B16: =B5-B14 -> 570.3
A18: GASTOS VARIÁVEIS | B18: Valor (R$)
A19: Crédito | B19: 203.5
A20: Lazer | B20: 250
A21: Investimentos | B21: 100
A22: Corte | B22: 0
A23: Imprevistos | B23: 0
A24: Total Variáveis | B24: =SUM(B19:B23) -> 553.5
A26: SALDO FINAL | B26: =B5-B14-B24 -> 16.8

Sheet Abril
A1: Controle de Gastos — Abril 2025
A2: RECEITAS | B2: Valor (R$)
A3: Salário | B3: 1960
A4: Comissão | B4: 500
A5: Total Receitas | B5: =SUM(B3:B4) -> 2460
A7: GASTOS FIXOS | B7: Valor (R$)
A8: Aluguel | B8: 880
A9: Luz | B9: 90
A10: Internet | B10: 59.9
A11: 4G | B11: 81.9
A12: Faculdade | B12: 157.9
A13: Alimentação | B13: 500
A14: Total Fixos | B14: =SUM(B8:B13) -> 1769.7
A16: Saldo após Fixos | B16: =B5-B14 -> 690.3
A18: GASTOS VARIÁVEIS | B18: Valor (R$)
A19: Crédito | B19: 213.81
A20: Lazer | B20: 247
A21: Investimentos | B21: 0
A22: Corte | B22: 30
A23: Imprevistos | B23: 0
A24: Total Variáveis | B24: =SUM(B19:B23) -> 490.81
A26: SALDO FINAL | B26: =B5-B14-B24 -> 199.49

Sheet Dados
A1: ⚠ Não edite esta aba manualmente. Dados espelho das abas mensais para uso em análises.
A2: Mês | B2: Categoria | C2: Tipo | D2: Valor (R$)
A3: Janeiro | B3: Aluguel | C3: Fixo | D3: 880
A4: Janeiro | B4: Luz | C4: Fixo | D4: 90
A5: Janeiro | B5: Internet | C5: Fixo | D5: 59.9
A6: Janeiro | B6: 4G | C6: Fixo | D6: 81.9
A7: Janeiro | B7: Faculdade | C7: Fixo | D7: 157.9
A8: Janeiro | B8: Alimentação | C8: Fixo | D8: 500
A9: Janeiro | B9: Crédito | C9: Variável | D9: 200.71
A10: Janeiro | B10: Lazer | C10: Variável | D10: 100
A11: Janeiro | B11: Investimentos | C11: Variável | D11: 183
A12: Janeiro | B12: Corte | C12: Variável | D12: 30
A13: Janeiro | B13: Imprevistos | C13: Variável | D13: 0
A14: Fevereiro | B14: Aluguel | C14: Fixo | D14: 880
... A46: Abril | B46: Imprevistos | C46: Variável | D46: 0
