Workbook

Sheet Janeiro
A1: Receitas
A2: Salário | B2: 1840
A3: Comissão | B3: 500
A4: Total Receitas | B4: =SUM(B2:B3) -> 2340
A6: Contas Fixas
A7: Aluguel | B7: 880
A8: Luz | B8: 90
A9: Internet | B9: 59.9
A10: 4g | B10: 81.9
A11: Faculdade | B11: 157.9
A12: Alimentação | B12: 500
A13: Total Fixo | B13: =SUM(B7:B12) -> 1769.7
A15: Saldo após fixas | B15: =B4-B13 -> 570.3
A17: Gastos Variáveis
A18: Crédito | B18: 200.71
A19: Lazer | B19: 100
A20: Investimentos | B20: 183
A21: Total Variável | B21: =SUM(B18:B20) -> 483.71
A23: Saldo Final | B23: =B15-B21 -> 86.59

Sheet Fevereiro
A1: Receitas
A2: Salário | B2: 2311
A3: Comissão | B3: 500
A4: Total Receitas | B4: =SUM(B2:B3) -> 2811
A6: Contas Fixas
A7: Aluguel | B7: 880
A8: Luz | B8: 90
A9: Internet | B9: 59.9
A10: 4g | B10: 81.9
A11: Faculdade | B11: 157.9
A12: Alimentação | B12: 500
A13: Total Fixo | B13: =SUM(B7:B12) -> 1769.7
A15: Saldo após fixas | B15: =B4-B13 -> 1041.3
A17: Gastos Variáveis
A18: Crédito | B18: 369.75
A19: Lazer | B19: 300
A20: Investimentos | B20: 206.65
A21: Total Variável | B21: =SUM(B18:B20) -> 876.4
A23: Saldo Final | B23: =B15-B21 -> 164.9

Sheet Março
A1: Receitas
A2: Salário | B2: 1840
A3: Comissão | B3: 500
A4: Total Receitas | B4: =SUM(B2:B3) -> 2340
A6: Contas Fixas
A7: Aluguel | B7: 880
A8: Luz | B8: 90
A9: Internet | B9: 59.9
A10: 4g | B10: 81.9
A11: Faculdade | B11: 157.9
A12: Alimentação | B12: 500
A13: Total Fixo | B13: =SUM(B7:B12) -> 1769.7
A15: Saldo após fixas | B15: =B4-B13 -> 570.3
A17: Gastos Variáveis
A18: Crédito | B18: 203.5
A19: Lazer | B19: 250
A20: Investimentos | B20: 100
A21: Total Variável | B21: =SUM(B18:B20) -> 553.5
A23: Saldo Final | B23: =B15-B21 -> 16.8

Sheet Abril
A1: Receitas
A2: Salário | B2: 1960
A3: Comissão | B3: 500
A4: Total Receitas | B4: =SUM(B2:B3) -> 2460
A6: Contas Fixas
A7: Aluguel | B7: 880
A8: Luz | B8: 90
A9: Internet | B9: 59.9
A10: 4g | B10: 81.9
A11: Faculdade | B11: 157.9
A12: Alimentação | B12: 500
A13: Total Fixo | B13: =SUM(B7:B12) -> 1769.7
A15: Saldo após fixas | B15: =B4-B13 -> 690.3
A17: Gastos Variáveis
A18: Crédito | B18: 213.81
A19: Lazer | B19: 100
A20: Investimentos
A21: Total Variável | B21: =SUM(B18:B20) -> 313.81
A23: Saldo Final | B23: =B15-B21 -> 376.49

Sheet Resumo
A1: Mês | B1: Receita | C1: Total Gasto | D1: Saldo Final
A2: Janeiro | B2: =Janeiro!B4 -> 2340 | C2: =Janeiro!B13+Janeiro!B21 -> 2253.41 | D2: =Janeiro!B23 -> 86.59
A3: Fevereiro | B3: =Fevereiro!B4 -> 2811 | C3: =Fevereiro!B13+Fevereiro!B21 -> 2646.1 | D3: =Fevereiro!B23 -> 164.9
A4: Março | B4: =Março!B4 -> 2340 | C4: =Março!B13+Março!B21 -> 2323.2 | D4: =Março!B23 -> 16.8
A5: Abril | B5: =Abril!B4 -> 2460 | C5: =Abril!B13+Abril!B21 -> 2083.51 | D5: =Abril!B23 -> 376.49
A6: Total | B6: =SUM(B2:B5) -> 9951 | C6: =SUM(C2:C5) -> 9306.22 | D6: =SUM(D2:D5) -> 644.78
